LICENSE
MANIFEST.in
README.rst
setup.py
chembl_beaker/__init__.py
chembl_beaker/run_beaker.py
chembl_beaker/tests.py
chembl_beaker.egg-info/PKG-INFO
chembl_beaker.egg-info/SOURCES.txt
chembl_beaker.egg-info/dependency_links.txt
chembl_beaker.egg-info/entry_points.txt
chembl_beaker.egg-info/not-zip-safe
chembl_beaker.egg-info/requires.txt
chembl_beaker.egg-info/top_level.txt
chembl_beaker/beaker/__init__.py
chembl_beaker/beaker/views.py
chembl_beaker/beaker/cache/__init__.py
chembl_beaker/beaker/cache/backends/__init__.py
chembl_beaker/beaker/cache/backends/base.py
chembl_beaker/beaker/cache/backends/locmem.py
chembl_beaker/beaker/cache/backends/memcached.py
chembl_beaker/beaker/cache/backends/mongo.py
chembl_beaker/beaker/cache/backends/sqlite.py
chembl_beaker/beaker/core_apps/__init__.py
chembl_beaker/beaker/core_apps/D3Coords/__init__.py
chembl_beaker/beaker/core_apps/D3Coords/impl.py
chembl_beaker/beaker/core_apps/D3Coords/views.py
chembl_beaker/beaker/core_apps/autoDocs/__init__.py
chembl_beaker/beaker/core_apps/autoDocs/views.py
chembl_beaker/beaker/core_apps/blast/__init__.py
chembl_beaker/beaker/core_apps/blast/impl.py
chembl_beaker/beaker/core_apps/blast/views.py
chembl_beaker/beaker/core_apps/calculations/__init__.py
chembl_beaker/beaker/core_apps/calculations/impl.py
chembl_beaker/beaker/core_apps/calculations/views.py
chembl_beaker/beaker/core_apps/conversions/__init__.py
chembl_beaker/beaker/core_apps/conversions/impl.py
chembl_beaker/beaker/core_apps/conversions/views.py
chembl_beaker/beaker/core_apps/descriptors/__init__.py
chembl_beaker/beaker/core_apps/descriptors/impl.py
chembl_beaker/beaker/core_apps/descriptors/views.py
chembl_beaker/beaker/core_apps/fingerprints/__init__.py
chembl_beaker/beaker/core_apps/fingerprints/impl.py
chembl_beaker/beaker/core_apps/fingerprints/views.py
chembl_beaker/beaker/core_apps/jsonImages/__init__.py
chembl_beaker/beaker/core_apps/jsonImages/impl.py
chembl_beaker/beaker/core_apps/jsonImages/jsonCanvas.py
chembl_beaker/beaker/core_apps/jsonImages/views.py
chembl_beaker/beaker/core_apps/marvin/MarvinJSONEncoder.py
chembl_beaker/beaker/core_apps/marvin/__init__.py
chembl_beaker/beaker/core_apps/marvin/impl.py
chembl_beaker/beaker/core_apps/marvin/views.py
